odoo/addons/contract_forecast/README.rst
odoo/addons/contract_forecast/__init__.py
odoo/addons/contract_forecast/__manifest__.py
odoo/addons/contract_forecast/hooks.py
odoo/addons/contract_forecast/i18n/contract_forecast.pot
odoo/addons/contract_forecast/i18n/de.po
odoo/addons/contract_forecast/i18n/es.po
odoo/addons/contract_forecast/i18n/fr.po
odoo/addons/contract_forecast/i18n/it.po
odoo/addons/contract_forecast/i18n/pt.po
odoo/addons/contract_forecast/i18n/pt_BR.po
odoo/addons/contract_forecast/migrations/12.0.1.0.1/post-migration.py
odoo/addons/contract_forecast/models/__init__.py
odoo/addons/contract_forecast/models/contract.py
odoo/addons/contract_forecast/models/contract_line.py
odoo/addons/contract_forecast/models/contract_line_forecast_period.py
odoo/addons/contract_forecast/models/res_company.py
odoo/addons/contract_forecast/models/res_config_settings.py
odoo/addons/contract_forecast/readme/CONTRIBUTORS.rst
odoo/addons/contract_forecast/readme/DESCRIPTION.rst
odoo/addons/contract_forecast/security/contract_line_forecast_period.xml
odoo/addons/contract_forecast/static/description/icon.png
odoo/addons/contract_forecast/static/description/index.html
odoo/addons/contract_forecast/tests/__init__.py
odoo/addons/contract_forecast/tests/test_contract_line_forecast_period.py
odoo/addons/contract_forecast/views/contract.xml
odoo/addons/contract_forecast/views/contract_line_forecast_period.xml
odoo/addons/contract_forecast/views/res_config_settings.xml
odoo12_addon_contract_forecast-12.0.1.2.0.dist-info/METADATA
odoo12_addon_contract_forecast-12.0.1.2.0.dist-info/WHEEL
odoo12_addon_contract_forecast-12.0.1.2.0.dist-info/top_level.txt
odoo12_addon_contract_forecast-12.0.1.2.0.dist-info/RECORD
