Metadata-Version: 2.1
Name: odoo12-addon-contract-forecast
Version: 12.0.1.2.0
Summary: Contract forecast
Home-page: https://github.com/OCA/contract
Author: ACSONE SA/NV,Odoo Community Association (OCA)
Author-email: support@odoo-community.org
License: AGPL-3
Platform: UNKNOWN
Classifier: Programming Language :: Python
Classifier: Framework :: Odoo
Classifier: License :: OSI Approved :: GNU Affero General Public License v3
Requires-Python: >=3.5
Requires-Dist: odoo12-addon-contract
Requires-Dist: odoo12-addon-queue-job
Requires-Dist: odoo (<12.1dev,>=12.0a)
Requires-Dist: python-dateutil
